pluglib/__init__.py
pluglib-0.0.0.dist-info/LICENSE
pluglib-0.0.0.dist-info/METADATA
pluglib-0.0.0.dist-info/WHEEL
pluglib-0.0.0.dist-info/top_level.txt
pluglib-0.0.0.dist-info/RECORD
