Metadata-Version: 2.1
Name: pluglib
Version: 0.0.0
Summary: A package used to create and import your plugs
Home-page: https://github.com/SandmX/pluglib
Author: Sandmeyer
Author-email: sandmx.work@gmail.com
Classifier: Programming Language :: Python :: 3
Classifier: License :: OSI Approved :: GNU General Public License v3 or later (GPLv3+)
Classifier: Operating System :: OS Independent
Requires-Python: >=3.6
License-File: LICENSE
